tpf/__init__.py
tpf/_d1_test.py
tpf/att.py
tpf/d1.py
tpf/d2.py
tpf/datasets.py
tpf/db.py
tpf/db2.py
tpf/db_ora.py
tpf/dbdoris.py
tpf/dl.py
tpf/dlt1.py
tpf/graph.py
tpf/install.py
tpf/layer.py
tpf/loss.py
tpf/metric.py
tpf/ml.py
tpf/params.py
tpf/tim.py
tpf/trans.py
tpf/vec.py
tpf/vec3.py
tpf/alg/__init__.py
tpf/alg/proba_stat.py
tpf/alg/sim.py
tpf/alg/tree/qianxu_2cha.py
tpf/box/__init__.py
tpf/box/base.py
tpf/box/emath.py
tpf/box/fil.py
tpf/box/zx.py
tpf/case/__init__.py
tpf/case/jiaoyi/__init__.py
tpf/case/jiaoyi/anli1.py
tpf/case/jiaoyi/anli1_v1.py
tpf/case/jiaoyi/anli1_v2.py
tpf/case/jiaoyi/anli1_v2_feature_gen.py
tpf/case/jiaoyi/anli1_v2_jwei.py
tpf/case/jiaoyi/anli1_v2_train-1.py
tpf/case/jiaoyi/breast_cancer_feature_selection_example.py
tpf/case/jiaoyi/datagen.py
tpf/case/jiaoyi/jiaoyi_sample.py
tpf/case/jiaoyi/liushui_test1.py
tpf/case/jiaoyi/liushui_test3.py
tpf/case/jiaoyi/main copy.py
tpf/case/jiaoyi/main.py
tpf/cn/__init__.py
tpf/cn/funcs.py
tpf/cn/funcs11.py
tpf/cn/funcs_bak.py
tpf/cn/funcs_tmp.py
tpf/cn/link.py
tpf/cn/prompt.py
tpf/cn/test.py
tpf/conf/__init__.py
tpf/conf/common.py
tpf/cv/__init__.py
tpf/cv/dataset.py
tpf/cv/lenet.py
tpf/cv/mtcnn.py
tpf/cv/resnet.py
tpf/cv/tools.py
tpf/data/__init__.py
tpf/data/deal.py
tpf/data/dtype.py
tpf/data/fenbu.py
tpf/data/make.py
tpf/data/make_fixed.py
tpf/data/read.py
tpf/data/sample.py
tpf/data/test_categorical_function.py
tpf/data/toolml.py
tpf/data/tu11.py
tpf/data/utils.py
tpf/data/feature/_FeatureSelected_test.py
tpf/data/feature/__init__.py
tpf/data/feature/_analyze_feature_importance.py
tpf/data/feature/_feature_comparison.py
tpf/data/feature/_selected_test.py
tpf/data/feature/_simple_test.py
tpf/data/feature/_test_feature_selection_lgbm.py
tpf/data/feature/config.py
tpf/data/feature/debug_normalize.py
tpf/data/feature/debug_test.py
tpf/data/feature/feature_comparison.py
tpf/data/feature/liushui copy.py
tpf/data/feature/liushui.py
tpf/data/feature/liushui_func.py
tpf/data/feature/liushui_func_test.py
tpf-1.0.60.dist-info/licenses/LICENSE
tpf-1.0.60.dist-info/METADATA
tpf-1.0.60.dist-info/WHEEL
tpf-1.0.60.dist-info/top_level.txt
tpf-1.0.60.dist-info/RECORD
