Metadata-Version: 2.4
Name: tpf
Version: 1.0.60
Summary: AI Common Methods Set
Author-email: Prentice Qisan <itoracle@163.com>
License-Expression: MIT
Project-URL: Homepage, https://gitee.com/star-spinning/tpf
Project-URL: Issues, https://gitee.com/star-spinning/tpf/issues
Requires-Python: >=3.8
License-File: LICENSE
Dynamic: license-file
